ldapregister/__init__.py
ldapregister/admin.py
ldapregister/apps.py
ldapregister/forms.py
ldapregister/models.py
ldapregister/views.py
ldapregister/migrations/0001_initial.py
ldapregister/migrations/0002_auto_20180215_1133.py
ldapregister/migrations/__init__.py
ldapregister/templates/base.html
ldapregister/templates/registration/login.html
ldapregister/templates/registration/logout.html
ldapregister/templates/registration/password_change_done.html
ldapregister/templates/registration/password_change_form.html
ldapregister/templates/registration/registration_closed.html
ldapregister/templates/registration/registration_form.html
ldh_middleware-0.0.3.data/data/config_sample/ldh_middleware/config.ini
ldh_middleware-0.0.3.data/data/config_sample/ldh_middleware/link_profile.strict.yml
ldh_middleware-0.0.3.data/data/config_sample/ldh_middleware/secret.ini
ldh_middleware-0.0.3.data/data/config_sample/nginx/purist_middleware
ldh_middleware-0.0.3.data/data/config_sample/supervisor/purist_middleware_monitor.conf
ldh_middleware-0.0.3.data/data/config_sample/uwsgi_emperor_vassals/purist_middleware.ini
ldh_middleware-0.0.3.data/scripts/ldh_middleware
ldh_middleware-0.0.3.dist-info/DESCRIPTION.rst
ldh_middleware-0.0.3.dist-info/METADATA
ldh_middleware-0.0.3.dist-info/RECORD
ldh_middleware-0.0.3.dist-info/WHEEL
ldh_middleware-0.0.3.dist-info/metadata.json
ldh_middleware-0.0.3.dist-info/top_level.txt
limitmonitor/__init__.py
limitmonitor/admin.py
limitmonitor/apps.py
limitmonitor/models.py
limitmonitor/tasks.py
limitmonitor/views.py
limitmonitor/jinja2/limitmonitor/userlimit.html
limitmonitor/migrations/0001_initial.py
limitmonitor/migrations/0002_auto_20171009_2334.py
limitmonitor/migrations/0003_auto_20171208_1327.py
limitmonitor/migrations/0004_auto_20180109_1139.py
limitmonitor/migrations/0005_auto_20180109_1211.py
limitmonitor/migrations/__init__.py
limitmonitor/task_resources/__init__.py
limitmonitor/task_resources/common.py
limitmonitor/task_resources/tunnel_credit.py
limitmonitor/task_resources/tunnel_subscription.py
middleware/__init__.py
middleware/celery.py
middleware/settings.py
middleware/settings_original.py
middleware/urls.py
middleware/wsgi.py
purist/__init__.py
