Metadata-Version: 2.0
Name: ldh-middleware
Version: 0.0.3
Summary: A middleware application (with a user-facing web interface) for managing subscription-based accounts on a Liberty Deckplan Host (LDH).
Home-page: https://source.puri.sm/liberty/ldh_middleware
Author: Purism SPC
Author-email: liberty@puri.sm
License: AGPL-3.0-or-later
Platform: UNKNOWN
Classifier: Programming Language :: Python :: 3
Classifier: Programming Language :: Python :: 3.5
Classifier: License :: OSI Approved :: GNU Affero General Public License v3 or later (AGPLv3+)
Requires-Dist: Jinja2 (==2.10)
Requires-Dist: celery (==4.1.1)
Requires-Dist: choicesenum (==0.2.2)
Requires-Dist: confusable-homoglyphs (==3.0.0)
Requires-Dist: dj-database-url (==0.4.2)
Requires-Dist: django (==1.11.18)
Requires-Dist: django-agpl (==4.0.0)
Requires-Dist: django-auth-ldap (==1.3.0)
Requires-Dist: django-celery-beat (==1.1.0)
Requires-Dist: django-crispy-forms (==1.7.0)
Requires-Dist: django-extensions (==1.9.9)
Requires-Dist: django-ldapdb (==0.9.0)
Requires-Dist: django-registration (==2.4.1)
Requires-Dist: jinja2-django-tags (==0.5)
Requires-Dist: paramiko (==2.4.1)
Requires-Dist: pyasn1 (==0.4.2)
Requires-Dist: python-decouple (==3.1)
Requires-Dist: python-ldap (==3.0.0)
Requires-Dist: strictyaml (==0.11.10)
Requires-Dist: woocommerce (==1.2.1)
